MANIFEST.in
README
changelog
copyright
setup.cfg
setup.py
bin/burn
bin/burn-configure
burn.egg-info/PKG-INFO
burn.egg-info/SOURCES.txt
burn.egg-info/dependency_links.txt
burn.egg-info/not-zip-safe
burn.egg-info/requires.txt
burn.egg-info/top_level.txt
burnlib/__init__.py
burnlib/audio.py
burnlib/burn.py
burnlib/configure.py
burnlib/console.py
burnlib/device.py
burnlib/interactive_configure.py
burnlib/version.py
doc/AUTHORS
doc/BUGS
doc/INSTALL
doc/KNOWN_BUGS
doc/TODO
doc/WISHLIST
doc/burn-configure.1.txt
doc/burn-flame.jpeg
doc/burn.1.txt
doc/burn.css
doc/docutils.conf
doc/index.txt
example/burn.conf
test/__init__.py
test/test_audio.py
test/test_configure.py
test/test_console.py
test/test_device.py
test/test_interactive_configure.py