Metadata-Version: 1.0
Name: burn
Version: 0.4.6
Summary: Command-line tool for writing optical media.
Home-page: http://www.bigpaul.org/burn/
Author: Ben Finney
Author-email: ben+python@benfinney.id.au
License: GPL-2+
Keywords: burn,cd,dvd,media
Platform: UNKNOWN
Classifier: License :: OSI Approved :: GNU General Public License (GPL)
Classifier: Development Status :: 4 - Beta
Classifier: Intended Audience :: End Users/Desktop
Classifier: Environment :: Console
Classifier: Operating System :: POSIX
Classifier: Operating System :: MacOS
Classifier: Programming Language :: Python
Classifier: Topic :: Multimedia :: Sound/Audio :: CD Audio :: CD Writing
Classifier: Topic :: System :: Archiving
Classifier: Topic :: Utilities
